genericache/__init__.py
genericache/digest.py
genericache/disk_cache.py
genericache/memory_cache.py
genericache/noop_cache.py
genericache/py.typed
genericache-0.5.2.dist-info/licenses/LICENSE
genericache-0.5.2.dist-info/METADATA
genericache-0.5.2.dist-info/WHEEL
genericache-0.5.2.dist-info/top_level.txt
genericache-0.5.2.dist-info/RECORD
