Metadata-Version: 2.4
Name: genericache
Version: 0.5.2
Summary: A thread-safe, process-safe cache for slow data fetching operations
Author-email: Tomaz Vieira <tom.fogaca@gmail.com>
Maintainer-email: Tomaz Vieira <tom.fogaca@gmail.com>
License-Expression: MIT
Project-URL: Repository, https://github.com/Tomaz-Vieira/genericache
Project-URL: Home-page, https://github.com/Tomaz-Vieira/genericache
Requires-Python: >=3.8
License-File: LICENSE
Requires-Dist: filelock>=3.16.1
Dynamic: license-file
